jenkins_job_builder_addons-1.0.4.dist-info/DESCRIPTION.rst
jenkins_job_builder_addons-1.0.4.dist-info/entry_points.txt
jenkins_job_builder_addons-1.0.4.dist-info/METADATA
jenkins_job_builder_addons-1.0.4.dist-info/metadata.json
jenkins_job_builder_addons-1.0.4.dist-info/pbr.json
jenkins_job_builder_addons-1.0.4.dist-info/RECORD
jenkins_job_builder_addons-1.0.4.dist-info/top_level.txt
jenkins_job_builder_addons-1.0.4.dist-info/WHEEL
jenkins_jobs_addons/__init__.py
jenkins_jobs_addons/folders.py
jenkins_jobs_addons/views.py
