Metadata-Version: 2.0
Name: jenkins-job-builder-addons
Version: 1.0.4
Summary: A suite of jenkins job builder addons
Home-page: https://github.com/jimbydamonk/jenkins-job-builder-addons
Author: Mike Buzzetti
Author-email: mike.buzzetti@gmail.com
License: Apache
Keywords: jenkins
Platform: UNKNOWN
Classifier: Development Status :: 2 - Pre-Alpha
Classifier: Intended Audience :: Developers
Classifier: License :: OSI Approved :: Apache Software License
Classifier: Natural Language :: English
Classifier: Programming Language :: Python :: 2
Classifier: Programming Language :: Python :: 2.6
Classifier: Programming Language :: Python :: 2.7
